conman/__init__.py
conman/constants.py
conman/io.py
conman/main.py
conman/utils.py
conman/commands/__init__.py
conman/commands/build.py
conman/commands/clean.py
conman/commands/init.py
conman/commands/status.py
conman/commands/update.py
conman/ressources/__init__.py
conman/ressources/devcontainer.py
conman/ressources/docker_compose.py
conman/ressources/docker_file.py
conman/templates/__init__.py
conman/templates/empty_template_.conman-config.yml
conman/templates/empty_template_Dockerfile-root
conman/templates/empty_template_Dockerfile-user
conman/templates/empty_template_devcontainer.json
conman/templates/empty_template_docker-compose-nvidia.yml
conman/templates/empty_template_docker-compose.yml
conman/templates/my_config_default.json
conman_tool-1.2.1.dist-info/LICENSE
conman_tool-1.2.1.dist-info/METADATA
conman_tool-1.2.1.dist-info/WHEEL
conman_tool-1.2.1.dist-info/entry_points.txt
conman_tool-1.2.1.dist-info/top_level.txt
conman_tool-1.2.1.dist-info/RECORD
