Metadata-Version: 2.1
Name: conman-tool
Version: 1.2.1
Summary: A Python tool for managing containers.
Home-page: https://github.com/elmokulc/conman.git
Author: Christian Elmo, Ludovic Charleux
Author-email: christianelmo@gmail.com
License: GPL v3
Platform: UNKNOWN
Classifier: Programming Language :: Python :: 3
Classifier: Programming Language :: Python :: 3 :: Only
Requires-Python: <3.11,>=3.8
Requires-Dist: pyyaml >=5.3.1
Requires-Dist: setuptools >=65.6.3
Requires-Dist: importlib-metadata >=6.0.1
